{"Websites": [{"Name": "Website 1", "url": "ankitt.tech", "download_res": true, "download_cors_res": true, "cors": true, "cors_download_res": true, "cors_download_cors_res": false, "max_cors": 1, "max_threads": 100, "same_origin_deviation": 4, "location": "C:\\Users\\Lenovo\\OneDrive\\Desktop\\Webber\\sites/1161955", "maintain_logs": true, "show_failed_files": true, "refetch": false, "logs": [], "hash": 1161955, "completed": true, "file_location": "C:\\Users\\Lenovo\\OneDrive\\Desktop\\Webber\\sites\\1161955\\ankitt.tech\\index.html"}, {"Name": "Website 1", "url": "ankitt.tech", "download_res": true, "download_cors_res": true, "cors": false, "cors_download_res": true, "cors_download_cors_res": false, "max_cors": 0, "max_threads": 100, "same_origin_deviation": 2, "location": "C:\\Users\\Lenovo\\OneDrive\\Desktop\\Webber\\sites/1207833", "maintain_logs": true, "show_failed_files": true, "refetch": false, "logs": [], "hash": 1207833, "completed": true, "file_location": "C:\\Users\\Lenovo\\OneDrive\\Desktop\\Webber\\sites\\1207833\\ankitt.tech\\index.html"}, {"Name": "Website 1", "url": "www.example.com", "download_res": true, "download_cors_res": true, "cors": false, "cors_download_res": true, "cors_download_cors_res": false, "max_cors": 0, "max_threads": 100, "same_origin_deviation": 2, "location": "C:\\bluff\\webber\\sites/1905889", "maintain_logs": true, "show_failed_files": true, "refetch": false, "logs": [], "hash": 1905889, "completed": true, "file_location": "C:\\bluff\\webber\\sites\\1905889\\www.example.com\\index.html"}, {"Name": "Website 1", "url": "www.example.com", "download_res": true, "download_cors_res": true, "cors": false, "cors_download_res": true, "cors_download_cors_res": false, "max_cors": 0, "max_threads": 100, "same_origin_deviation": 2, "location": "C:\\bluff\\webber\\sites/1093631", "maintain_logs": true, "show_failed_files": true, "refetch": false, "logs": [], "hash": 1093631, "completed": false, "file_location": "C:\\bluff\\webber\\sites\\1093631\\www.example.com\\index.html"}, {"Name": "Website 1", "url": "www.example.com", "download_res": true, "download_cors_res": true, "cors": false, "cors_download_res": true, "cors_download_cors_res": false, "max_cors": 0, "max_threads": 100, "same_origin_deviation": 2, "location": "C:\\bluff\\webber\\sites/1604588", "maintain_logs": true, "show_failed_files": true, "refetch": false, "logs": [], "hash": 1604588, "completed": false, "file_location": "C:\\bluff\\webber\\sites\\1604588\\www.example.com\\index.html"}, {"Name": "Website 1", "url": "www.example.com", "download_res": true, "download_cors_res": true, "cors": false, "cors_download_res": true, "cors_download_cors_res": false, "max_cors": 0, "max_threads": 100, "same_origin_deviation": 2, "location": "C:\\bluff\\webber\\sites/1493409", "maintain_logs": true, "show_failed_files": true, "refetch": false, "logs": [], "hash": 1493409, "completed": false, "file_location": "C:\\bluff\\webber\\sites\\1493409\\www.example.com\\index.html"}, {"Name": "Website 1", "url": "www.example.com", "download_res": true, "download_cors_res": true, "cors": false, "cors_download_res": true, "cors_download_cors_res": false, "max_cors": 0, "max_threads": 100, "same_origin_deviation": 2, "location": "C:\\bluff\\webber\\sites/1213950", "maintain_logs": true, "show_failed_files": true, "refetch": false, "logs": [], "hash": 1213950, "completed": true, "file_location": "C:\\bluff\\webber\\sites\\1213950\\www.example.com\\index.html"}]}